{
  "name": "Hellion",
  "color": "RED",
  "rechargeCost": ["RED","YELLOW"],
  "cost": ["YELLOW"],
  "primaryEffect": [
    {
      "input": ["TARGET","TARGET","TARGET","TARGET"],
      "cost": null,
      "actions": [
        {
          "name": "SHOOT_ONE_AWAY_VIEW",
          "parameters": [
            "TARGET.0"
          ]
        },
        {
          "name": "MARK_ONE_AWAY_VIEW",
          "parameters": [
            "TARGET.0"
          ]
        },
        {
          "name": "MARK_EVERY_ONE_AWAY_VIEW",
          "parameters": [
            "TARGET.1",
            "TARGET.2",
            "TARGET.3"
          ]
        }
      ]
    },
    {
      "input": ["TARGET","TARGET","TARGET","TARGET"],
      "cost": ["RED"],
      "actions": [
        {
          "name": "SHOOT_ONE_AWAY_VIEW",
          "parameters": [
            "TARGET.0"
          ]
        },
        {
          "name": "MARK__ONE_AWAY_VIEW",
          "parameters": [
            "TARGET.0"
          ]
        },
        {
          "name": "MARK__ONE_AWAY_VIEW",
          "parameters": [
            "TARGET.0"
          ]
        },
        {
          "name": "MARK_EVERY_ONE_AWAY_VIEW",
          "parameters": [
            "TARGET.1",
            "TARGET.2",
            "TARGET.3"
          ]
        },
        {
          "name": "MARK_EVERY_ONE_AWAY_VIEW",
          "parameters": [
            "TARGET.1",
            "TARGET.2",
            "TARGET.3"
          ]
        }
      ]
    }

  ]
}
