{
  "name": "Zx2",
  "color": "YELLOW",
  "rechargeCost": ["YELLOW","RED"],
  "cost": ["RED"],
  "primaryEffect": [
    {
      "input": ["TARGET"],
      "cost": null,
      "actions": [
        {
          "type": "SHOOT_VIEW",
          "parameters": [
            "TARGET.0"
          ]
        },
        {
          "type": "MARK_VIEW",
          "parameters": [
            "TARGET.0"
          ]
        },
        {
          "type": "MARK_VIEW",
          "parameters": [
            "TARGET.0"
          ]
        }
      ]
    },
    {
      "input": ["TARGET","TARGET","TARGET"],
      "cost": null,
      "actions": [
        {
          "type": "SHOOT_VIEW",
          "parameters": [
            "TARGET.0"
          ]
        },
        {
          "type": "SHOOT_VIEW",
          "parameters": [
            "TARGET.1"
          ]
        },
        {
          "type": "SHOOT_VIEW",
          "parameters": [
            "TARGET.2"
          ]
        }
      ]
    }
  ]
}

